freewili/__init__.py
freewili/_version.py
freewili/cli.py
freewili/cli_convert.py
freewili/cli_serial.py
freewili/frame_parser.py
freewili/framing.py
freewili/fw.py
freewili/fw_serial.py
freewili/image.py
freewili/safe_response_frame_dict.py
freewili/serialport.py
freewili/types.py
freewili/util/__init__.py
freewili/util/fifo.py
freewili-0.0.49.dist-info/METADATA
freewili-0.0.49.dist-info/WHEEL
freewili-0.0.49.dist-info/entry_points.txt
freewili-0.0.49.dist-info/RECORD
