Metadata-Version: 2.4
Name: freewili
Version: 0.0.49
Project-URL: Homepage, https://freewili.com/
Project-URL: Repository, https://github.com/freewili/freewili-python
Project-URL: Documentation, https://freewili.github.io/freewili-python/
Author-email: David Rebbe <drebbe@intrepidcs.com>
License: MIT
Keywords: freewili
Requires-Python: >=3.10
Requires-Dist: numpy>=2.2.4
Requires-Dist: pillow==12.1.0
Requires-Dist: pyfwfinder==0.4.2
Requires-Dist: pyserial==3.5
Requires-Dist: result==0.17.0
Requires-Dist: typing-extensions==4.12.2
